palworld_save_tools/__init__.py
palworld_save_tools/archive.py
palworld_save_tools/gvas.py
palworld_save_tools/json_tools.py
palworld_save_tools/palsav.py
palworld_save_tools/paltypes.py
palworld_save_tools/commands/__init__.py
palworld_save_tools/commands/convert.py
palworld_save_tools/commands/resave_test.py
palworld_save_tools/rawdata/__init__.py
palworld_save_tools/rawdata/base_camp.py
palworld_save_tools/rawdata/base_camp_module.py
palworld_save_tools/rawdata/build_process.py
palworld_save_tools/rawdata/character.py
palworld_save_tools/rawdata/character_container.py
palworld_save_tools/rawdata/common.py
palworld_save_tools/rawdata/connector.py
palworld_save_tools/rawdata/debug.py
palworld_save_tools/rawdata/dynamic_item.py
palworld_save_tools/rawdata/foliage_model.py
palworld_save_tools/rawdata/foliage_model_instance.py
palworld_save_tools/rawdata/group.py
palworld_save_tools/rawdata/item_container.py
palworld_save_tools/rawdata/item_container_slots.py
palworld_save_tools/rawdata/map_concrete_model.py
palworld_save_tools/rawdata/map_concrete_model_module.py
palworld_save_tools/rawdata/map_model.py
palworld_save_tools/rawdata/map_object.py
palworld_save_tools/rawdata/work.py
palworld_save_tools/rawdata/work_collection.py
palworld_save_tools/rawdata/worker_director.py
palworld_save_tools-0.24.0.dist-info/METADATA
palworld_save_tools-0.24.0.dist-info/WHEEL
palworld_save_tools-0.24.0.dist-info/entry_points.txt
palworld_save_tools-0.24.0.dist-info/licenses/LICENSE
palworld_save_tools-0.24.0.dist-info/RECORD
