Metadata-Version: 2.3
Name: palworld-save-tools
Version: 0.24.0
Summary: Tools for converting Palworld .sav files to JSON and back
Project-URL: Homepage, https://github.com/cheahjs/palworld-save-tools
Project-URL: Issues, https://github.com/cheahjs/palworld-save-tools/issues
Author-email: Jun Siang Cheah <me@jscheah.me>
License-File: LICENSE
Classifier: License :: OSI Approved :: MIT License
Classifier: Operating System :: OS Independent
Classifier: Programming Language :: Python :: 3
Requires-Python: >=3.9
Provides-Extra: performance
Requires-Dist: recordclass; extra == 'performance'
Provides-Extra: tests
Requires-Dist: mypy==1.8.0; extra == 'tests'
Requires-Dist: parameterized==0.9.0; extra == 'tests'
